setup.py
PyPokerEngine.egg-info/PKG-INFO
PyPokerEngine.egg-info/SOURCES.txt
PyPokerEngine.egg-info/dependency_links.txt
PyPokerEngine.egg-info/top_level.txt
examples/__init__.py
examples/players/__init__.py
examples/players/console_player.py
examples/players/emulator_player.py
examples/players/fish_player.py
examples/players/fold_man.py
examples/players/honest_player.py
examples/players/random_player.py
pypokerengine/__init__.py
pypokerengine/players.py
pypokerengine/api/__init__.py
pypokerengine/api/emulator.py
pypokerengine/api/game.py
pypokerengine/engine/__init__.py
pypokerengine/engine/action_checker.py
pypokerengine/engine/card.py
pypokerengine/engine/data_encoder.py
pypokerengine/engine/dealer.py
pypokerengine/engine/deck.py
pypokerengine/engine/game_evaluator.py
pypokerengine/engine/hand_evaluator.py
pypokerengine/engine/message_builder.py
pypokerengine/engine/pay_info.py
pypokerengine/engine/player.py
pypokerengine/engine/poker_constants.py
pypokerengine/engine/round_manager.py
pypokerengine/engine/seats.py
pypokerengine/engine/table.py
pypokerengine/utils/__init__.py
pypokerengine/utils/action_utils.py
pypokerengine/utils/card_utils.py
pypokerengine/utils/game_state_utils.py
pypokerengine/utils/visualize_utils.py
tests/examples/__init__.py
tests/examples/players/__init__.py
tests/examples/players/console_player_test.py
tests/pypokerengine/__init__.py
tests/pypokerengine/api/__init__.py
tests/pypokerengine/api/emulator_test.py
tests/pypokerengine/api/game_test.py
tests/pypokerengine/engine/__init__.py
tests/pypokerengine/engine/action_checker_test.py
tests/pypokerengine/engine/card_test.py
tests/pypokerengine/engine/data_encoder_test.py
tests/pypokerengine/engine/dealer_message_handler_test.py
tests/pypokerengine/engine/dealer_message_integration_test.py
tests/pypokerengine/engine/dealer_message_summarizer_test.py
tests/pypokerengine/engine/dealer_test.py
tests/pypokerengine/engine/deck_test.py
tests/pypokerengine/engine/game_evaluator_test.py
tests/pypokerengine/engine/hand_evaluator_test.py
tests/pypokerengine/engine/message_builder_test.py
tests/pypokerengine/engine/pay_info_test.py
